mockwebserver/__init__.py
mockwebserver/mockwebserver.py
mockwebserver-0.5.0.dist-info/METADATA
mockwebserver-0.5.0.dist-info/RECORD
mockwebserver-0.5.0.dist-info/WHEEL
mockwebserver-0.5.0.dist-info/top_level.txt
tests/__init__.py
tests/test_mockwebserver.py
