Metadata-Version: 2.1
Name: mockwebserver
Version: 0.5.0
Summary: A simple web server for unit testing purposes. Acts as context manager for teardown.
Home-page: https://github.com/Virtualstock/mockwebserver
Author: Virtualstock
Author-email: dev.admin@virtualstock.com
License: UNKNOWN
Platform: UNKNOWN
Requires-Dist: attrs
Requires-Dist: wsgi-intercept (==1.5.1)
Requires-Dist: requests
